verilog_files/good_mux.v
module good_mux(
input i0,
input i1,
input sel,
output y
);
assign y = sel ? i1 : i0;

endmodule

verilog_files/tb_good_mux.v
module tb_good_mux;
reg i0;
reg i1;
reg sel;
wire y;
 good_mux uut (
          .i0(i0),
          .i1(i1),
          .sel(sel),
          .y(y)
);

initial begin 
        $dumpfile("tb_good_mux.vcd");
        $dumpvars(0, tb_good_mux);

        i0 = 0;
        i1=0;
        sel=0;
 
   #300 $finish;
end

always #10 i0 = ~i0;
always #55 i1 = ~i1;
always #75 sel = ~sel;

endmodule

verilog_files/tb_good_mux.vcd
$date
	Sat Aug 15 16:06:42 2026
$end
$version
	Icarus Verilog
$end
$timescale
	1s
$end
$scope module tb_good_mux $end
$var wire 1 ! y $end
$var reg 1 " i0 $end
$var reg 1 # i1 $end
$var reg 1 $ sel $end
$scope module uut $end
$var wire 1 " i0 $end
$var wire 1 # i1 $end
$var wire 1 $ sel $end
$var wire 1 ! y $end
$upscope $end
$upscope $end
$enddefinitions $end
$comment Show the parameter values. $end
$dumpall
$end
#0
$dumpvars
0$
0#
0"
0!
$end
#10
1!
1"
#20
0!
0"
#30
1!
1"
#40
0!
0"
#50
1!
1"
#55
1#
#60
0!
0"
#70
1!
1"
#75
1$
#80
0"
#90
1"
#100
0"
#110
0!
1"
0#
#120
0"
#130
1"
#140
0"
#150
1!
1"
0$
#160
0!
0"
#165
1#
#170
1!
1"
#180
0!
0"
#190
1!
1"
#200
0!
0"
#210
1!
1"
#220
0!
0"
0#
#225
1$
#230
1"
#240
0"
#250
1"
#260
0"
#270
1"
#275
1!
1#
#280
0"
#290
1"
#300
0!
0"
0$
